xontrib/comands_cache_predictors.py
xontrib/json_syslog_history_backend.py
xontrib/syslog-shell-profiler.xsh
xontrib_syslog_shell_profiler-0.1.5.dist-info/METADATA
xontrib_syslog_shell_profiler-0.1.5.dist-info/WHEEL
xontrib_syslog_shell_profiler-0.1.5.dist-info/top_level.txt
xontrib_syslog_shell_profiler-0.1.5.dist-info/RECORD
